jijzept_dashboard_client/__init__.py
jijzept_dashboard_client/client.py
jijzept_dashboard_client/exception.py
jijzept_dashboard_client/problem.py
jijzept_dashboard_client/schema.py
jijzept_dashboard_client-0.1.4.dist-info/LICENSE.txt
jijzept_dashboard_client-0.1.4.dist-info/METADATA
jijzept_dashboard_client-0.1.4.dist-info/WHEEL
jijzept_dashboard_client-0.1.4.dist-info/RECORD
