Metadata-Version: 2.1
Name: jijzept_dashboard_client
Version: 0.1.4
Summary: 
License: LICENSE.txt
Author: Jij Inc.
Requires-Python: >=3.9
Classifier: License :: Other/Proprietary License
Classifier: Programming Language :: Python :: 3
Classifier: Programming Language :: Python :: 3.9
Classifier: Programming Language :: Python :: 3.10
Classifier: Programming Language :: Python :: 3.11
Classifier: Programming Language :: Python :: 3.12
Requires-Dist: jijmodeling (>=1.4.1,<2.0.0)
Requires-Dist: protobuf (>=5.26.1,<6.0.0)
Requires-Dist: pydantic (>=2.6.4,<3.0.0)
Requires-Dist: requests (>=2.32.2,<3.0.0)
